mzdata2mat/__init__.py
mzdata2mat/classes.py
mzdata2mat/errors.py
mzdata2mat/mzdata2mat.py
mzdata2mat/tiny1.mzData.xml
mzdata2mat-0.2.0.dist-info/METADATA
mzdata2mat-0.2.0.dist-info/WHEEL
mzdata2mat-0.2.0.dist-info/entry_points.txt
mzdata2mat-0.2.0.dist-info/licenses/LICENSE.txt
mzdata2mat-0.2.0.dist-info/RECORD
