Metadata-Version: 2.3
Name: mzdata2mat
Version: 0.2.0
Summary: Package used to convert mzData.xml files version 1.05 into matlab files.
Project-URL: Documentation, https://mzdata2mat.readthedocs.io/
Project-URL: Repository, https://github.com/MaximeLeMagicien/mzdata2mat.git
Project-URL: Issues, https://github.com/MaximeLeMagicien/mzdata2mat/issues
Project-URL: Changelog, https://github.com/MaximeLeMagicien/mzdata2mat/blob/main/docs/source/Changelog.md
Author-email: LARTIC <christophe.cordella@fsaa.ulaval.ca>
Maintainer-email: CORDELLA Maxime <maxime.cordella911@gmail.com>, CORDELLA Christophe <christophe.cordella@fsaa.ulaval.ca>
License: MIT License
License-File: LICENSE.txt
Keywords: .mat,.mzData.xml,.xml,convert,matlab,mzData
Classifier: Development Status :: 4 - Beta
Classifier: License :: OSI Approved :: MIT License
Classifier: Natural Language :: English
Classifier: Operating System :: MacOS :: MacOS X
Classifier: Operating System :: Microsoft :: Windows :: Windows 11
Classifier: Programming Language :: Python :: 3
Classifier: Programming Language :: Python :: 3.9
Classifier: Programming Language :: Python :: 3.10
Classifier: Programming Language :: Python :: 3.11
Classifier: Programming Language :: Python :: 3.12
Requires-Python: >=3.9
Requires-Dist: colorama>=0.4.6
Requires-Dist: javascript>=1!1.1.3
Requires-Dist: mat4py>=0.6.0
Requires-Dist: pydantic>=2.6.4
